gslogger/__init__.py
gslogger/extras.py
gslogger/glog.py
gslogger/jin.py
gslogger/version.py
gslogger-0.2.72.dist-info/METADATA
gslogger-0.2.72.dist-info/WHEEL
gslogger-0.2.72.dist-info/entry_points.txt
gslogger-0.2.72.dist-info/licenses/LICENSE
gslogger-0.2.72.dist-info/RECORD
